LICENSE
MANIFEST.in
README.rst
pyproject.toml
setup.py
pytest_stoq/__init__.py
pytest_stoq/fixtures.py
pytest_stoq/plugin.py
pytest_stoq/stoq.py
pytest_stoq.egg-info/PKG-INFO
pytest_stoq.egg-info/SOURCES.txt
pytest_stoq.egg-info/dependency_links.txt
pytest_stoq.egg-info/entry_points.txt
pytest_stoq.egg-info/requires.txt
pytest_stoq.egg-info/top_level.txt