Metadata-Version: 1.2
Name: pytest-stoq
Version: 0.7.2
Summary: A plugin to pytest stoq
Home-page: https://github.com/stoq/pytest-stoq
Author: Stoq Team
Author-email: stoq-devel@async.com.br
Maintainer: Stoq Team
Maintainer-email: stoq-devel@async.com.br
License: GNU GPL v3.0
Platform: UNKNOWN
Classifier: Development Status :: 4 - Beta
Classifier: Framework :: Pytest
Classifier: Intended Audience :: Developers
Classifier: Topic :: Software Development :: Testing
Classifier: Programming Language :: Python :: 3
Classifier: Programming Language :: Python :: 3.4
Classifier: Programming Language :: Python :: 3.5
Classifier: Programming Language :: Python :: 3.6
Classifier: Programming Language :: Python :: 3.7
Classifier: Programming Language :: Python :: Implementation :: CPython
Classifier: Programming Language :: Python :: Implementation :: PyPy
Classifier: Operating System :: OS Independent
Classifier: License :: OSI Approved :: GNU General Public License v3 (GPLv3)
Requires-Python: >=3.4
